m3inference/__init__.py
m3inference/consts.py
m3inference/dataset.py
m3inference/full_model.py
m3inference/m3inference.py
m3inference/m3twitter.py
m3inference/preprocess.py
m3inference/text_model.py
m3inference/utils.py
m3inference/data/emb.pkl
m3inference/data/tw_default_profile.png
m3inference-1.1.5.dist-info/LICENSE
m3inference-1.1.5.dist-info/METADATA
m3inference-1.1.5.dist-info/WHEEL
m3inference-1.1.5.dist-info/top_level.txt
m3inference-1.1.5.dist-info/RECORD
