Metadata-Version: 2.1
Name: m3inference
Version: 1.1.5
Summary: M3 Inference
Home-page: https://github.com/euagendas/m3inference
Author: Zijian Wang et al.
Author-email: zijwang@stanford.edu
License: GNU Affero General Public License v3.0
Platform: UNKNOWN
Requires-Python: >=3.6
Requires-Dist: torch (>=1.0.0)
Requires-Dist: numpy (>=1.13)
Requires-Dist: tqdm
Requires-Dist: Pillow
Requires-Dist: torchvision (>=0.2.2)
Requires-Dist: pycld2 (>=0.31)
Requires-Dist: requests
Requires-Dist: pandas (>=0.20)
Requires-Dist: rauth
